prompttube.py
prompttube_sdk-0.1.1.dist-info/METADATA
prompttube_sdk-0.1.1.dist-info/WHEEL
prompttube_sdk-0.1.1.dist-info/top_level.txt
prompttube_sdk-0.1.1.dist-info/RECORD
