Metadata-Version: 2.4
Name: prompttube-sdk
Version: 0.1.1
Summary: Tiny Python wrapper for the PromptTube Public API v0.
Author: PromptTube
License-Expression: MIT
Requires-Python: >=3.9
